{"tileKey":"la_m47_lo_m70","version":"v1-1775891056926","entries":[{"id":"node:4436616359","kind":"peak","name":"Cerro Piedra","lat":-46.2907219,"lon":-69.8452148,"elevationM":713},{"id":"node:4436616360","kind":"peak","name":"Cerro Slapelez","lat":-46.0762339,"lon":-69.9444866,"elevationM":643},{"id":"node:4436670657","kind":"peak","name":"Cerro Bandera","lat":-46.2126547,"lon":-69.2172937,"elevationM":543},{"id":"node:4436670658","kind":"peak","name":"Cerro Bayo","lat":-46.1583922,"lon":-69.039794,"elevationM":454},{"id":"node:4436670659","kind":"peak","name":"Bayo","lat":-46.7004616,"lon":-69.1970155,"elevationM":596},{"id":"node:4436670660","kind":"peak","name":"Cerro Buitre","lat":-46.7367496,"lon":-69.727587,"elevationM":483},{"id":"node:4436670661","kind":"peak","name":"Cerro Chapalala","lat":-46.6214901,"lon":-69.7053967,"elevationM":478},{"id":"node:4436670662","kind":"peak","name":"Cerro Cuadrado","lat":-46.324723,"lon":-69.4228172,"elevationM":738},{"id":"node:4436670664","kind":"peak","name":"Cerro El Guadal","lat":-46.4602376,"lon":-69.3363733,"elevationM":675},{"id":"node:4436670675","kind":"peak","name":"Cerro Setenta","lat":-46.4659945,"lon":-69.1018341,"elevationM":672},{"id":"node:4436670676","kind":"peak","name":"Cerro Sombrero","lat":-46.7272665,"lon":-69.7997706,"elevationM":434},{"id":"node:4436670679","kind":"peak","name":"Wenceslao","lat":-46.5982368,"lon":-69.0420959,"elevationM":569},{"id":"node:4436670682","kind":"peak","name":"Loma de Cuy","lat":-46.3855242,"lon":-69.119019,"elevationM":598},{"id":"node:4436776397","kind":"peak","name":"Bonete","lat":-46.8640069,"lon":-69.2375622,"elevationM":1006},{"id":"node:4436776400","kind":"peak","name":"Chenque","lat":-46.7671671,"lon":-69.1246376,"elevationM":396},{"id":"node:4436776405","kind":"peak","name":"El Centinela","lat":-46.9797596,"lon":-69.0969572,"elevationM":597},{"id":"node:4436776422","kind":"peak","name":"Tres Picos","lat":-46.8997846,"lon":-69.22962,"elevationM":1028},{"id":"node:4436776428","kind":"peak","name":"Los Moleres","lat":-46.9829847,"lon":-69.188904,"elevationM":776},{"id":"node:4444550144","kind":"peak","name":"Cerro Yique","lat":-46.8252459,"lon":-69.9405861,"elevationM":734}]}