{"tileKey":"la_p62_lo_m65","version":"v1-1775891056926","entries":[{"id":"node:4094356210","kind":"peak","name":"Mount Dillon","lat":62.5198483,"lon":-64.3921906,"elevationM":null},{"id":"node:11345785432","kind":"peak","name":"Mount Budington","lat":62.9052587,"lon":-64.8719272,"elevationM":null},{"id":"node:11345785539","kind":"peak","name":"Mount Warwick","lat":62.5412822,"lon":-64.2129249,"elevationM":null},{"id":"node:11345785555","kind":"peak","name":"Jones Tower","lat":62.5340045,"lon":-64.6927302,"elevationM":null}]}