{"tileKey":"la_p46_lo_m124","version":"v1-1775891056926","entries":[{"id":"node:348187456","kind":"peak","name":"Michigan Hill","lat":46.7764894,"lon":-123.1168065,"elevationM":142},{"id":"node:348187460","kind":"peak","name":"Capitol Peak","lat":46.9731529,"lon":-123.138082,"elevationM":787},{"id":"node:348187466","kind":"peak","name":"Grand Mound Peak","lat":46.7968875,"lon":-123.0337467,"elevationM":73},{"id":"node:348187467","kind":"peak","name":"Mount Molly","lat":46.9537084,"lon":-123.0895892,"elevationM":344},{"id":"node:348187468","kind":"peak","name":"Larch Mountain","lat":46.9873188,"lon":-123.1376475,"elevationM":774},{"id":"node:348187477","kind":"peak","name":"Little Larch Mountain","lat":46.9570636,"lon":-123.1174859,"elevationM":342},{"id":"node:348190163","kind":"peak","name":"Stony Grade","lat":46.4853839,"lon":-123.0090119,"elevationM":308},{"id":"node:348190168","kind":"peak","name":"Point Hill","lat":46.4781607,"lon":-123.0881837,"elevationM":220},{"id":"node:348190171","kind":"peak","name":"Sure Shot Mountain","lat":46.4764934,"lon":-123.1406873,"elevationM":517},{"id":"node:348190176","kind":"peak","name":"Sam Henry Mountain","lat":46.5162165,"lon":-123.0206804,"elevationM":462},{"id":"node:348190179","kind":"peak","name":"Crego Hill","lat":46.5548265,"lon":-123.0587402,"elevationM":437},{"id":"node:348190182","kind":"peak","name":"Ceres Hill","lat":46.6192689,"lon":-123.1559704,"elevationM":239},{"id":"node:348190186","kind":"peak","name":"Pleasant Hill","lat":46.59427,"lon":-123.0851322,"elevationM":269},{"id":"node:348190198","kind":"peak","name":"Cook Hill","lat":46.7181574,"lon":-123.0476347,"elevationM":176},{"id":"node:348190208","kind":"peak","name":"Bucks Knob","lat":46.6820453,"lon":-123.3337591,"elevationM":725},{"id":"node:348190226","kind":"peak","name":"Ferrier Peak","lat":46.4031611,"lon":-123.2134657,"elevationM":721},{"id":"node:348190234","kind":"peak","name":"Cherry Hill","lat":46.5867683,"lon":-123.2626427,"elevationM":226},{"id":"node:348190246","kind":"peak","name":"Little Mountain","lat":46.4717711,"lon":-123.15041,"elevationM":479},{"id":"node:348190257","kind":"peak","name":"Buckhorn Hill","lat":46.541216,"lon":-123.0251263,"elevationM":398},{"id":"node:348190261","kind":"peak","name":"Little Onion","lat":46.421494,"lon":-123.2059663,"elevationM":808},{"id":"node:348190263","kind":"peak","name":"Joy Mountain","lat":46.5339911,"lon":-123.2568083,"elevationM":535},{"id":"node:348190266","kind":"peak","name":"Boistfort Peak","lat":46.48778,"lon":-123.2145022,"elevationM":941},{"id":"node:348190282","kind":"peak","name":"Clinton Knob","lat":46.4162169,"lon":-123.1598521,"elevationM":727},{"id":"node:348190287","kind":"peak","name":"Round Knob","lat":46.4842969,"lon":-123.1860445,"elevationM":617},{"id":"node:348192473","kind":"peak","name":"Abernathy Mountain","lat":46.335386,"lon":-123.0954004,"elevationM":770},{"id":"node:348192475","kind":"peak","name":"Pumphrey Mountain","lat":46.3712699,"lon":-123.0057619,"elevationM":457},{"id":"node:348517886","kind":"peak","name":"Hay Mountain","lat":46.2076098,"lon":-123.2706798,"elevationM":338},{"id":"node:348517897","kind":"peak","name":"Beare Hill","lat":46.2679756,"lon":-123.5721621,"elevationM":318},{"id":"node:348517905","kind":"peak","name":"KM Mountain","lat":46.3420522,"lon":-123.5101401,"elevationM":276},{"id":"node:348517914","kind":"peak","name":"Moe Hill","lat":46.279191,"lon":-123.4770882,"elevationM":270},{"id":"node:348517926","kind":"peak","name":"Rangila Hill","lat":46.3445505,"lon":-123.6765339,"elevationM":142},{"id":"node:348517968","kind":"peak","name":"Cape Horn","lat":46.1520546,"lon":-123.2873457,"elevationM":29},{"id":"node:348517975","kind":"peak","name":"Deep River Hill","lat":46.3809385,"lon":-123.6890366,"elevationM":225},{"id":"node:348517981","kind":"peak","name":"Salme Hill","lat":46.3556609,"lon":-123.7215359,"elevationM":172},{"id":"node:348517986","kind":"peak","name":"Hogans Hill","lat":46.2764981,"lon":-123.4304102,"elevationM":326},{"id":"node:348518029","kind":"peak","name":"Lutes Mountain","lat":46.2821695,"lon":-123.4870186,"elevationM":332},{"id":"node:348518041","kind":"peak","name":"Elk Mountain","lat":46.3279553,"lon":-123.5508756,"elevationM":459},{"id":"node:348518052","kind":"peak","name":"Altoona Hill","lat":46.277123,"lon":-123.6302613,"elevationM":369},{"id":"node:348526413","kind":"peak","name":"Bear Mountain","lat":46.2976048,"lon":-123.8198688,"elevationM":308},{"id":"node:348526429","kind":"peak","name":"Pluvius Hill","lat":46.5509362,"lon":-123.4115381,"elevationM":260},{"id":"node:348526445","kind":"peak","name":"Squally Jim","lat":46.5887137,"lon":-123.4429293,"elevationM":625},{"id":"node:348526460","kind":"peak","name":"Walville Peak","lat":46.5895468,"lon":-123.4159835,"elevationM":735},{"id":"node:348526485","kind":"peak","name":"Longfellow Hill","lat":46.3814932,"lon":-123.7701499,"elevationM":294},{"id":"node:348617215","kind":"peak","name":"Scar Hill","lat":46.8564859,"lon":-123.6929406,"elevationM":272},{"id":"node:348617362","kind":"peak","name":"Blue Mountain","lat":46.8256545,"lon":-123.4626575,"elevationM":533},{"id":"node:348617376","kind":"peak","name":"Fuzzy Top","lat":46.9386431,"lon":-123.1655937,"elevationM":462},{"id":"node:348617403","kind":"peak","name":"Minot Peak","lat":46.8920422,"lon":-123.4179343,"elevationM":544},{"id":"node:356539916","kind":"peak","name":"Crown Point","lat":46.2803793,"lon":-123.3480161,"elevationM":550},{"id":"node:357279003","kind":"peak","name":"Clatskanie Mountain","lat":46.0664997,"lon":-123.2842881,"elevationM":625},{"id":"node:357279431","kind":"peak","name":"Coxcomb Hill","lat":46.1813092,"lon":-123.8175757,"elevationM":172},{"id":"node:357280293","kind":"peak","name":"Elk Mountain","lat":46.0414998,"lon":-123.5692966,"elevationM":816},{"id":"node:357285228","kind":"peak","name":"Nicolai Mountain","lat":46.0870553,"lon":-123.4592943,"elevationM":902},{"id":"node:357292598","kind":"peak","name":"Sister Green Mountain","lat":46.0095549,"lon":-123.7609679,"elevationM":521},{"id":"node:357297404","kind":"peak","name":"Knob Point","lat":46.112333,"lon":-123.5040185,"elevationM":632},{"id":"node:357297415","kind":"peak","name":"Tunnel Mountain","lat":46.085944,"lon":-123.3429016,"elevationM":407},{"id":"node:357297428","kind":"peak","name":"Benson Point","lat":46.0401112,"lon":-123.2109517,"elevationM":569},{"id":"node:357303281","kind":"peak","name":"Palm Hill","lat":46.1128883,"lon":-123.2281761,"elevationM":149},{"id":"node:357304783","kind":"peak","name":"Wickiup Mountain","lat":46.1059436,"lon":-123.5862431,"elevationM":807},{"id":"node:11021349665","kind":"peak","name":"Green Mountain","lat":46.0185723,"lon":-123.7055976,"elevationM":623},{"id":"node:11062761809","kind":"peak","name":"Megler Mountain","lat":46.2640553,"lon":-123.8869393,"elevationM":323},{"id":"node:11365268662","kind":"peak","name":"Snow Point","lat":46.0170885,"lon":-123.6714421,"elevationM":null},{"id":"node:11365268666","kind":"peak","name":"Windy Mountain","lat":46.0271558,"lon":-123.1850619,"elevationM":null},{"id":"node:13250197604","kind":"peak","name":"Flash Mountain","lat":46.9893481,"lon":-123.1305603,"elevationM":909}]}