{"tileKey":"la_p22_lo_p93","version":"v1-1775891056926","entries":[{"id":"node:490522124","kind":"peak","name":"Mount Phabipa","lat":22.1085381,"lon":93.2475509,"elevationM":null},{"id":"node:4801959251","kind":"peak","name":"Mount Zinghmuh","lat":22.7885624,"lon":93.550029,"elevationM":2565},{"id":"node:5668372777","kind":"peak","name":"Mount Zinghmuh","lat":22.8263185,"lon":93.5393261,"elevationM":2565},{"id":"node:6210406657","kind":"peak","name":"Phawngpui Peak","lat":22.6177149,"lon":93.0474508,"elevationM":2157}]}