{"tileKey":"la_p48_lo_p138","version":"v1-1775891056926","entries":[{"id":"node:3351398124","kind":"peak","name":"Тордоки-Яни","lat":48.8970236,"lon":138.053772,"elevationM":2090},{"id":"node:10564500200","kind":"peak","name":"Сагды-Бяха","lat":48.9814107,"lon":138.8569159,"elevationM":1521},{"id":"node:10732335718","kind":"peak","name":"Яко","lat":48.6812563,"lon":138.2482185,"elevationM":1955},{"id":"node:10732335719","kind":"peak","name":"Яко-Яни","lat":48.6577154,"lon":138.1638863,"elevationM":1681},{"id":"node:10732335720","kind":"peak","name":"Бо-Джауса","lat":48.1416286,"lon":138.7246628,"elevationM":1637},{"id":"node:10732335721","kind":"peak","name":"Джауса","lat":48.5767406,"lon":138.8048351,"elevationM":1326},{"id":"node:10732335723","kind":"peak","name":"Дзюба","lat":48.7265948,"lon":138.3330699,"elevationM":1811},{"id":"node:13075331333","kind":"peak","name":"гора Снежная","lat":48.401272,"lon":138.1892752,"elevationM":1606},{"id":"node:13109882382","kind":"peak","name":"гора Маяк","lat":48.442846,"lon":138.2416427,"elevationM":1494},{"id":"node:13143549323","kind":"peak","name":"г. Моховая","lat":48.0330865,"lon":138.577466,"elevationM":1364},{"id":"node:13143631071","kind":"peak","name":"г. Лесная","lat":48.226942,"lon":138.5255063,"elevationM":1335},{"id":"node:13143631073","kind":"peak","name":"г. Гордая","lat":48.1906742,"lon":138.571254,"elevationM":1534},{"id":"node:13143631083","kind":"peak","name":"г. Лысая","lat":48.1886178,"lon":138.718577,"elevationM":1334},{"id":"node:13545371866","kind":"peak","name":"г. Сама","lat":48.0215267,"lon":138.0858133,"elevationM":1097},{"id":"node:13545371868","kind":"peak","name":"г. Неприступная","lat":48.2546084,"lon":138.0347474,"elevationM":1414},{"id":"node:13545371874","kind":"peak","name":"г. Половодье","lat":48.0271173,"lon":138.2737887,"elevationM":774},{"id":"node:13545371875","kind":"peak","name":"г. Оумская","lat":48.0520731,"lon":138.2175239,"elevationM":726},{"id":"node:13545371876","kind":"peak","name":"г. Маркелова","lat":48.1023483,"lon":138.2902063,"elevationM":1169},{"id":"node:13545371877","kind":"peak","name":"г. Командная","lat":48.1720244,"lon":138.3583617,"elevationM":841},{"id":"node:13545371878","kind":"peak","name":"г. Лесная Скала","lat":48.1951729,"lon":138.3193946,"elevationM":1000},{"id":"node:13545371880","kind":"peak","name":"г. Ясная","lat":48.2679121,"lon":138.3476329,"elevationM":1009}]}