{"tileKey":"la_p56_lo_m62","version":"v1-1775891056926","entries":[{"id":"node:7310454037","kind":"peak","name":"Man O'War Peak","lat":56.9684216,"lon":-61.6711736,"elevationM":null},{"id":"node:7310454038","kind":"peak","name":"Webb Hill","lat":56.8013483,"lon":-61.7835474,"elevationM":null},{"id":"node:7310454040","kind":"peak","name":"Webb Knoll","lat":56.7397094,"lon":-61.7490006,"elevationM":null},{"id":"node:7310454041","kind":"peak","name":"Tikkiraluk Hill","lat":56.715765,"lon":-61.7382288,"elevationM":null},{"id":"node:7310454042","kind":"peak","name":"Sakotalik Summit","lat":56.6345539,"lon":-61.6965795,"elevationM":null},{"id":"node:7310454043","kind":"peak","name":"Mount Thoresby","lat":56.9206103,"lon":-61.4589143,"elevationM":null},{"id":"node:7310454044","kind":"peak","name":"Backsight Hill","lat":56.8573844,"lon":-61.3970733,"elevationM":null},{"id":"node:7310454045","kind":"peak","name":"Mist Hill","lat":56.8238174,"lon":-61.5730262,"elevationM":null},{"id":"node:7310454046","kind":"peak","name":"Kolotulik Hill","lat":56.7972007,"lon":-61.5328145,"elevationM":null},{"id":"node:7310454047","kind":"peak","name":"Itilialuk Hill","lat":56.6820946,"lon":-61.6844559,"elevationM":null},{"id":"node:7310454048","kind":"peak","name":"Blackface Hill","lat":56.7516759,"lon":-61.390121,"elevationM":null},{"id":"node:7310454049","kind":"peak","name":"Two Stone Hill","lat":56.7479934,"lon":-61.4193678,"elevationM":null},{"id":"node:7310454050","kind":"peak","name":"Amerak","lat":56.7230771,"lon":-61.4712954,"elevationM":null},{"id":"node:7310454051","kind":"peak","name":"The Peak","lat":56.6969897,"lon":-61.383555,"elevationM":null},{"id":"node:7310454052","kind":"peak","name":"Ballybrack Hill","lat":56.6719452,"lon":-61.389091,"elevationM":null},{"id":"node:7310454053","kind":"peak","name":"Low Point Hill","lat":56.6830375,"lon":-61.5370846,"elevationM":null},{"id":"node:7310454054","kind":"peak","name":"Nuluk Knoll","lat":56.6522044,"lon":-61.4923668,"elevationM":null},{"id":"node:7310454055","kind":"peak","name":"South Hill","lat":56.6314323,"lon":-61.4430678,"elevationM":null},{"id":"node:7310454056","kind":"peak","name":"Needles Knoll","lat":56.6039291,"lon":-61.3956356,"elevationM":null},{"id":"node:7310454057","kind":"peak","name":"Nixon Hill","lat":56.6481346,"lon":-61.5412045,"elevationM":null},{"id":"node:7310454058","kind":"peak","name":"Satosuakuluk Hill","lat":56.6508361,"lon":-61.5823388,"elevationM":null},{"id":"node:7310454059","kind":"peak","name":"Camp Hill","lat":56.6199293,"lon":-61.5681982,"elevationM":null},{"id":"node:7310454060","kind":"peak","name":"Seal Hill","lat":56.5974916,"lon":-61.5541649,"elevationM":null},{"id":"node:7310454061","kind":"peak","name":"Iviyanguyak Peaks","lat":56.5847966,"lon":-61.5304327,"elevationM":null},{"id":"node:7310454062","kind":"peak","name":"Iviyanguyak Peaks","lat":56.5905687,"lon":-61.5463007,"elevationM":null},{"id":"node:7310454063","kind":"peak","name":"Eve Knoll","lat":56.5848616,"lon":-61.4370811,"elevationM":null},{"id":"node:7310454064","kind":"peak","name":"Hayes Cone","lat":56.6873687,"lon":-61.1592901,"elevationM":null},{"id":"node:7310454065","kind":"peak","name":"Alagaiai Hill","lat":56.6758179,"lon":-61.124475,"elevationM":null},{"id":"node:7310454066","kind":"peak","name":"Oakes Cone","lat":56.6613155,"lon":-61.1556959,"elevationM":null},{"id":"node:7310454067","kind":"peak","name":"Naksaluk Hill","lat":56.5991454,"lon":-61.214726,"elevationM":null},{"id":"node:7310454068","kind":"peak","name":"The Consul","lat":56.5088271,"lon":-61.7358899,"elevationM":null},{"id":"node:7310454069","kind":"peak","name":"Ship Hill","lat":56.5162504,"lon":-61.7275858,"elevationM":null},{"id":"node:7310454070","kind":"peak","name":"South Channel Cairn","lat":56.5255659,"lon":-61.6580415,"elevationM":null},{"id":"node:7310454071","kind":"peak","name":"Riflesight Hill","lat":56.5144332,"lon":-61.6170037,"elevationM":null},{"id":"node:7310454072","kind":"peak","name":"Scotch Hill","lat":56.4891549,"lon":-61.6101265,"elevationM":null},{"id":"node:7310454073","kind":"peak","name":"Bridges Hill","lat":56.4662898,"lon":-61.6168964,"elevationM":null},{"id":"node:7310454074","kind":"peak","name":"Dick Hill","lat":56.4640435,"lon":-61.5915978,"elevationM":null},{"id":"node:7310454075","kind":"peak","name":"Anchor Knoll","lat":56.4586256,"lon":-61.5462685,"elevationM":null},{"id":"node:7310454076","kind":"peak","name":"Tinigivik Hill","lat":56.4516049,"lon":-61.4837746,"elevationM":null},{"id":"node:7310454077","kind":"peak","name":"Mount Pownal","lat":56.4661566,"lon":-61.4306911,"elevationM":null},{"id":"node:7310454078","kind":"peak","name":"Sentinel Hill","lat":56.4244458,"lon":-61.542653,"elevationM":null},{"id":"node:7310454079","kind":"peak","name":"Kikkertavak Hill","lat":56.4035493,"lon":-61.6552312,"elevationM":null},{"id":"node:7310454080","kind":"peak","name":"White Hill","lat":56.3018937,"lon":-61.9666294,"elevationM":null},{"id":"node:7310454082","kind":"peak","name":"Garland Hat Hill","lat":56.2085423,"lon":-61.7950539,"elevationM":null}]}