{"tileKey":"la_p44_lo_p1","version":"v1-1775891056926","entries":[{"id":"node:388743659","kind":"peak","name":"Pech Laprune","lat":44.9612008,"lon":1.6225753,"elevationM":311},{"id":"node:1075523789","kind":"peak","name":"Pech Mercier","lat":44.4799551,"lon":1.7490801,"elevationM":366},{"id":"node:1397299808","kind":"peak","name":"La Roc de Garde","lat":44.8281944,"lon":1.1231113,"elevationM":210},{"id":"node:2870437740","kind":"peak","name":"Roc d'Anglars","lat":44.1442234,"lon":1.7653834,"elevationM":null},{"id":"node:5312555588","kind":"peak","name":"Rocher de Cayla","lat":44.8566496,"lon":1.8577352,"elevationM":291},{"id":"node:6767272365","kind":"peak","name":"Roc Deymié","lat":44.1539339,"lon":1.7655292,"elevationM":null},{"id":"node:6772918301","kind":"peak","name":"Roc de l'aigle","lat":44.1363899,"lon":1.7199809,"elevationM":null},{"id":"node:6772918302","kind":"peak","name":"Falaise des capucins","lat":44.1501963,"lon":1.7189191,"elevationM":null},{"id":"node:6818146804","kind":"peak","name":"Pech de Lacave","lat":44.841698,"lon":1.5677726,"elevationM":272},{"id":"node:6934906724","kind":"peak","name":"Pech Lauzié","lat":44.7816808,"lon":1.4913613,"elevationM":333},{"id":"node:6935254673","kind":"peak","name":"Le Pech de Gramont","lat":44.7746871,"lon":1.3838164,"elevationM":180},{"id":"node:7057922531","kind":"peak","name":"Mont Saint-Joseph","lat":44.8165029,"lon":1.8630357,"elevationM":609},{"id":"node:8084739060","kind":"peak","name":"Pech de Belcastel","lat":44.8385605,"lon":1.5430791,"elevationM":225},{"id":"node:8596920386","kind":"peak","name":"Pech de Gourbière","lat":44.8338338,"lon":1.591022,"elevationM":356},{"id":"node:8596920387","kind":"peak","name":"Pech de Bouriane","lat":44.8171665,"lon":1.6423923,"elevationM":305},{"id":"node:8596920388","kind":"peak","name":"Pipou (Les Bruges)","lat":44.8728233,"lon":1.4648222,"elevationM":null},{"id":"node:8596920389","kind":"peak","name":"Pech Merle","lat":44.9055746,"lon":1.4451938,"elevationM":256},{"id":"node:8596920390","kind":"peak","name":"Rignac","lat":44.9412685,"lon":1.5102094,"elevationM":323},{"id":"node:8596920391","kind":"peak","name":"Pech des Batailles","lat":44.7210412,"lon":1.5106786,"elevationM":437},{"id":"node:8596920392","kind":"peak","name":"Église de Lunegarde","lat":44.690373,"lon":1.6884244,"elevationM":432},{"id":"node:8596920394","kind":"peak","name":"Pech de Rode","lat":44.7087419,"lon":1.6574246,"elevationM":null},{"id":"node:8597915314","kind":"peak","name":"Mont Mercou","lat":44.9121947,"lon":1.5821353,"elevationM":316},{"id":"node:8618610969","kind":"peak","name":"Pech Roudé","lat":44.7813461,"lon":1.5413273,"elevationM":268},{"id":"node:9199132598","kind":"peak","name":"Pech Mioule","lat":44.543909,"lon":1.8424687,"elevationM":332},{"id":"node:9315056803","kind":"peak","name":"Côte Saint-Julien","lat":44.1294833,"lon":1.7012234,"elevationM":null},{"id":"node:9315056804","kind":"peak","name":"La Côte Neuve","lat":44.1257065,"lon":1.7056483,"elevationM":null},{"id":"node:9315056805","kind":"peak","name":"La Côte Veille","lat":44.1200798,"lon":1.7047864,"elevationM":null},{"id":"node:9315135448","kind":"peak","name":"Côte Trémoulayre","lat":44.1812181,"lon":1.582347,"elevationM":null},{"id":"node:9315135451","kind":"peak","name":"Roc du Saut","lat":44.1811792,"lon":1.585699,"elevationM":null},{"id":"node:9316262385","kind":"peak","name":"Pech Trégon","lat":44.0284759,"lon":1.6816746,"elevationM":371},{"id":"node:9316295048","kind":"peak","name":"Les Colombiers","lat":44.0718814,"lon":1.658216,"elevationM":229},{"id":"node:9319270121","kind":"peak","name":"Puech Calm","lat":44.173971,"lon":1.8874452,"elevationM":null},{"id":"node:9330680709","kind":"peak","name":"Pech de Bourgues","lat":44.130071,"lon":1.8113727,"elevationM":249},{"id":"node:9335557642","kind":"peak","name":"La Mothe","lat":44.1801898,"lon":1.8430876,"elevationM":306},{"id":"node:9335625152","kind":"peak","name":"Au Plassoulètes","lat":44.1884091,"lon":1.8416545,"elevationM":371},{"id":"node:9335625158","kind":"peak","name":"Pech de Ginals","lat":44.1910533,"lon":1.8552703,"elevationM":263},{"id":"node:9335627437","kind":"peak","name":"Pech Fournié","lat":44.2039714,"lon":1.8835606,"elevationM":393},{"id":"node:9389455347","kind":"peak","name":"Pech Saint-Bressou","lat":44.7052472,"lon":1.9685908,"elevationM":619},{"id":"node:9390786784","kind":"peak","name":"Pech Maurel","lat":44.2449631,"lon":1.9537364,"elevationM":504},{"id":"node:9399333099","kind":"peak","name":"Les Carbonnières","lat":44.5569166,"lon":1.9224924,"elevationM":400},{"id":"node:9399333100","kind":"peak","name":"Les Garennes","lat":44.5451439,"lon":1.9155911,"elevationM":413},{"id":"node:9399333101","kind":"peak","name":"Pech Bourru","lat":44.5262282,"lon":1.9230266,"elevationM":390},{"id":"node:9399333102","kind":"peak","name":"Bouscailloux","lat":44.5575306,"lon":1.8819055,"elevationM":402},{"id":"node:9399333104","kind":"peak","name":"Puy-Manau","lat":44.5478205,"lon":1.893667,"elevationM":400},{"id":"node:9399333105","kind":"peak","name":"Le Château","lat":44.5383215,"lon":1.8855574,"elevationM":400},{"id":"node:9399333106","kind":"peak","name":"La Peyrade","lat":44.5772419,"lon":1.8869102,"elevationM":403},{"id":"node:9399333107","kind":"peak","name":"Fouille-douze","lat":44.5782432,"lon":1.870183,"elevationM":395},{"id":"node:9399333108","kind":"peak","name":"Ligoussou","lat":44.6123443,"lon":1.8546595,"elevationM":442},{"id":"node:9399333109","kind":"peak","name":"Les Cambous","lat":44.4003205,"lon":1.9977913,"elevationM":440},{"id":"node:9399333110","kind":"peak","name":"Pech Caudie","lat":44.430496,"lon":1.9945363,"elevationM":440},{"id":"node:9399333111","kind":"peak","name":"Le Fangassou","lat":44.5253538,"lon":1.8013807,"elevationM":393},{"id":"node:9399333112","kind":"peak","name":"Pech Piolat","lat":44.5293601,"lon":1.7903612,"elevationM":380},{"id":"node:9399333114","kind":"peak","name":"Pech Granat","lat":44.520584,"lon":1.8397512,"elevationM":389},{"id":"node:9399481597","kind":"peak","name":"La Plane","lat":44.0847376,"lon":1.8341825,"elevationM":529},{"id":"node:9399481598","kind":"peak","name":"Le Lac","lat":44.0797835,"lon":1.8150653,"elevationM":512},{"id":"node:9399481599","kind":"peak","name":"Le Castelet","lat":44.055185,"lon":1.7592436,"elevationM":493},{"id":"node:9399481601","kind":"peak","name":"Belle la Croix","lat":44.2111468,"lon":1.938778,"elevationM":507},{"id":"node:9399481602","kind":"peak","name":"Les Carats","lat":44.2296003,"lon":1.9461468,"elevationM":505},{"id":"node:9402756420","kind":"peak","name":"Bigorre","lat":44.3294931,"lon":1.8212789,"elevationM":411},{"id":"node:9402756421","kind":"peak","name":"Pech de Guerre","lat":44.3620516,"lon":1.7849135,"elevationM":403},{"id":"node:9402756422","kind":"peak","name":"Pech Bayssou","lat":44.3432752,"lon":1.7599261,"elevationM":409},{"id":"node:9402756423","kind":"peak","name":"Pech Audou","lat":44.3839169,"lon":1.808348,"elevationM":407},{"id":"node:9416501795","kind":"peak","name":"Puech Fourbal","lat":44.2518824,"lon":1.9807192,"elevationM":489},{"id":"node:9444633691","kind":"peak","name":"Puech de Linchirie","lat":44.2568729,"lon":1.9871829,"elevationM":471},{"id":"node:9804695081","kind":"peak","name":"Pech de Marty","lat":44.1187365,"lon":1.1673366,"elevationM":146},{"id":"node:9846466894","kind":"peak","name":"Rocher Sainte-Marie","lat":44.8668897,"lon":1.5767839,"elevationM":263},{"id":"node:10972149091","kind":"peak","name":"Rocher de Peine","lat":44.9337951,"lon":1.0154495,"elevationM":null},{"id":"node:11377754471","kind":"peak","name":"Puy de Tour","lat":44.9895109,"lon":1.6825762,"elevationM":251},{"id":"node:11377768115","kind":"peak","name":"Puy d'Issolud","lat":44.9562015,"lon":1.6797803,"elevationM":311},{"id":"node:11397324331","kind":"peak","name":"Pech Pendit","lat":44.8179687,"lon":1.8861912,"elevationM":628},{"id":"node:11401494133","kind":"peak","name":"Pech de Lapale","lat":44.9147893,"lon":1.9704972,"elevationM":566},{"id":"node:11401548750","kind":"peak","name":"Pech de Clédy","lat":44.9102242,"lon":1.9421549,"elevationM":525},{"id":"node:11479454455","kind":"peak","name":"Puy Turlau","lat":44.9884547,"lon":1.7586014,"elevationM":277},{"id":"node:12022929937","kind":"peak","name":"Puech d'Albet","lat":44.8970993,"lon":1.990255,"elevationM":572},{"id":"node:12022930119","kind":"peak","name":"Puech Laborderie","lat":44.8978429,"lon":1.9799314,"elevationM":547},{"id":"node:12022930156","kind":"peak","name":"Puech del Moulé","lat":44.9040291,"lon":1.9861111,"elevationM":525},{"id":"node:12022942912","kind":"peak","name":"Puech Naufret","lat":44.9049507,"lon":1.9902072,"elevationM":544},{"id":"node:12023038935","kind":"peak","name":"Puech de la Deveze","lat":44.8670031,"lon":1.9978855,"elevationM":527},{"id":"node:12023086704","kind":"peak","name":"Puech Usclat","lat":44.881437,"lon":1.9808636,"elevationM":520},{"id":"node:12023086706","kind":"peak","name":"Puech del Bos","lat":44.8825403,"lon":1.990248,"elevationM":548},{"id":"node:12023086708","kind":"peak","name":"Puech d'Asfaux","lat":44.8816843,"lon":1.97511,"elevationM":530},{"id":"node:12023086733","kind":"peak","name":"Puech Long","lat":44.8857313,"lon":1.9853315,"elevationM":546},{"id":"node:12023086753","kind":"peak","name":"Puech d'Herbouze","lat":44.9048157,"lon":1.9987108,"elevationM":581},{"id":"node:12033327347","kind":"peak","name":"Pech Castanié","lat":44.4611413,"lon":1.4655311,"elevationM":230},{"id":"node:12033327348","kind":"peak","name":"Mont Saint-Cyr","lat":44.4425136,"lon":1.4543746,"elevationM":266},{"id":"node:12033327361","kind":"peak","name":"Pech de la Vignasse","lat":44.4491463,"lon":1.4891791,"elevationM":291},{"id":"node:12154137477","kind":"peak","name":"Puech Juanès","lat":44.9391857,"lon":1.995407,"elevationM":544},{"id":"node:12154137480","kind":"peak","name":"Pech de Bergne-Nègre","lat":44.9354987,"lon":1.9911799,"elevationM":520},{"id":"node:12154137486","kind":"peak","name":"Pech de Labastide","lat":44.9397552,"lon":1.9988152,"elevationM":532},{"id":"node:12154137487","kind":"peak","name":"Pech de la Croix longue","lat":44.9444835,"lon":1.9983661,"elevationM":560},{"id":"node:12154137497","kind":"peak","name":"Pech Cani","lat":44.9273717,"lon":1.9889211,"elevationM":546},{"id":"node:12154137498","kind":"peak","name":"Pech Roland","lat":44.9298776,"lon":1.9874336,"elevationM":560},{"id":"node:12154137500","kind":"peak","name":"Pech Gros","lat":44.9175524,"lon":1.9933132,"elevationM":565},{"id":"node:12154137504","kind":"peak","name":"Peh Niauzel","lat":44.9207387,"lon":1.9791608,"elevationM":561},{"id":"node:12154137507","kind":"peak","name":"Pech de la Bille","lat":44.9287111,"lon":1.9707726,"elevationM":547},{"id":"node:12154137509","kind":"peak","name":"Pech de Carla","lat":44.9310713,"lon":1.9716009,"elevationM":560},{"id":"node:12154137513","kind":"peak","name":"Pech Mialet","lat":44.9312912,"lon":1.9813791,"elevationM":530},{"id":"node:12154137520","kind":"peak","name":"Pech Labade","lat":44.9441023,"lon":1.9670979,"elevationM":543},{"id":"node:12154195747","kind":"peak","name":"Pech Tourtoulou","lat":44.9583604,"lon":1.9726191,"elevationM":475},{"id":"node:12154195750","kind":"peak","name":"Pech Maco","lat":44.9605651,"lon":1.9806587,"elevationM":538},{"id":"node:12154195760","kind":"peak","name":"Pech Franjau","lat":44.9642578,"lon":1.9800552,"elevationM":506},{"id":"node:12292194249","kind":"peak","name":"Pech de Mazuc","lat":44.3797703,"lon":1.7697846,"elevationM":315},{"id":"node:12387767039","kind":"peak","name":"Pech de Lafont","lat":44.970742,"lon":1.592501,"elevationM":297},{"id":"node:12387767040","kind":"peak","name":"Pech Chausens","lat":44.9828523,"lon":1.591438,"elevationM":312},{"id":"node:12396211572","kind":"peak","name":"Puy Perrier","lat":44.9966507,"lon":1.9083456,"elevationM":426},{"id":"node:12403352575","kind":"peak","name":"Pech d'Embrieu","lat":44.8750187,"lon":1.8738916,"elevationM":305},{"id":"node:12403352578","kind":"peak","name":"Pech Roussy","lat":44.8610244,"lon":1.9171925,"elevationM":313},{"id":"node:12413626007","kind":"peak","name":"Puech de Lagoux","lat":44.9264642,"lon":1.9722298,"elevationM":566},{"id":"node:12413626008","kind":"peak","name":"Puech de Garde","lat":44.9332099,"lon":1.9588874,"elevationM":542},{"id":"node:12420983756","kind":"peak","name":"Coste Lauze","lat":44.9372384,"lon":1.9373949,"elevationM":442},{"id":"node:12420983757","kind":"peak","name":"Pech d'Endreuille","lat":44.8890188,"lon":1.9409209,"elevationM":460},{"id":"node:12568937013","kind":"peak","name":"Côte-d'Aubié","lat":44.8546151,"lon":1.9821635,"elevationM":505},{"id":"node:12569139110","kind":"peak","name":"Pech Redon","lat":44.9677379,"lon":1.9370407,"elevationM":501},{"id":"node:12569139111","kind":"peak","name":"Puech Lacabane","lat":44.9684612,"lon":1.9198387,"elevationM":466},{"id":"node:12569139112","kind":"peak","name":"Pech de Cardaillac","lat":44.9612066,"lon":1.9322835,"elevationM":497},{"id":"node:12569172817","kind":"peak","name":"Pech Pillar","lat":44.9003964,"lon":1.8427721,"elevationM":261},{"id":"node:12569172821","kind":"peak","name":"Pech Cayroux","lat":44.8800456,"lon":1.7937639,"elevationM":334},{"id":"node:12569172822","kind":"peak","name":"Puy de Garrissou","lat":44.8775576,"lon":1.7532424,"elevationM":370},{"id":"node:12569172823","kind":"peak","name":"Puy de Tillou","lat":44.8688988,"lon":1.7542209,"elevationM":362},{"id":"node:12569172824","kind":"peak","name":"Pech du Roc","lat":44.8672856,"lon":1.744074,"elevationM":346},{"id":"node:12569172825","kind":"peak","name":"Le Pech","lat":44.8732772,"lon":1.7373363,"elevationM":332},{"id":"node:12569385869","kind":"peak","name":"Pech de Frayruc","lat":44.4399461,"lon":1.5378029,"elevationM":250},{"id":"node:12569385870","kind":"peak","name":"Pech de la Barre","lat":44.4420667,"lon":1.5305364,"elevationM":240},{"id":"node:12569385871","kind":"peak","name":"Pech de Vignoles","lat":44.4501174,"lon":1.5143755,"elevationM":null},{"id":"node:12569385872","kind":"peak","name":"Pech Louis","lat":44.4493451,"lon":1.5443966,"elevationM":233},{"id":"node:12569385873","kind":"peak","name":"Pech Crabel","lat":44.481012,"lon":1.4740501,"elevationM":269},{"id":"node:12569385874","kind":"peak","name":"Pech de Coutal","lat":44.4892347,"lon":1.4774498,"elevationM":289},{"id":"node:12569385875","kind":"peak","name":"Pech de Planiac","lat":44.4933656,"lon":1.4836329,"elevationM":308},{"id":"node:12569385876","kind":"peak","name":"Cap Nau Haut","lat":44.4551969,"lon":1.4190174,"elevationM":269},{"id":"node:12571311035","kind":"peak","name":"La Césarine","lat":44.8504182,"lon":1.854613,"elevationM":352},{"id":"node:12571311036","kind":"peak","name":"Le Caussenil","lat":44.8542821,"lon":1.8495524,"elevationM":322},{"id":"node:12571311037","kind":"peak","name":"Causse de Lauriol","lat":44.84199,"lon":1.8645372,"elevationM":371},{"id":"node:12571311038","kind":"peak","name":"Causse de Benne","lat":44.8407754,"lon":1.852435,"elevationM":403},{"id":"node:12571311039","kind":"peak","name":"Pech de Maute","lat":44.8684641,"lon":1.8175564,"elevationM":301},{"id":"node:12571311040","kind":"peak","name":"Pech Daudu","lat":44.8843565,"lon":1.797665,"elevationM":263},{"id":"node:12571311041","kind":"peak","name":"Pech Carlux","lat":44.8806164,"lon":1.8106469,"elevationM":237},{"id":"node:12571311042","kind":"peak","name":"La Proucisse","lat":44.879993,"lon":1.8592301,"elevationM":272},{"id":"node:12571311043","kind":"peak","name":"Le Ségala","lat":44.8851539,"lon":1.8578498,"elevationM":293},{"id":"node:12571366452","kind":"peak","name":"Pech del Tour","lat":44.8470159,"lon":1.5719047,"elevationM":284},{"id":"node:12571366453","kind":"peak","name":"Pech del Raysse","lat":44.8527966,"lon":1.5715399,"elevationM":257},{"id":"node:12571366454","kind":"peak","name":"Pech Grizou","lat":44.8569645,"lon":1.5752521,"elevationM":210},{"id":"node:12571366455","kind":"peak","name":"Pech de la Téoulo","lat":44.8347455,"lon":1.5359745,"elevationM":245},{"id":"node:12571366456","kind":"peak","name":"Causse de Bourgnou","lat":44.8317119,"lon":1.5403643,"elevationM":245},{"id":"node:12571366457","kind":"peak","name":"Montgignes","lat":44.862286,"lon":1.5998875,"elevationM":235},{"id":"node:12571366458","kind":"peak","name":"Pech d'Aussel","lat":44.8750845,"lon":1.6038621,"elevationM":256},{"id":"node:12571366459","kind":"peak","name":"Le Peyrazet","lat":44.9061053,"lon":1.6090387,"elevationM":221},{"id":"node:12571369249","kind":"peak","name":"Pech Lasserre","lat":44.9091347,"lon":1.6744093,"elevationM":291},{"id":"node:12571369250","kind":"peak","name":"Pech de Souly","lat":44.9135264,"lon":1.6934852,"elevationM":325},{"id":"node:12571369251","kind":"peak","name":"Pech Bartas","lat":44.9066423,"lon":1.6917686,"elevationM":312},{"id":"node:12585438212","kind":"peak","name":"Pech du Village","lat":44.9072006,"lon":1.8940137,"elevationM":335},{"id":"node:12585645436","kind":"peak","name":"Roc Bataillet","lat":44.9250672,"lon":1.3567594,"elevationM":264},{"id":"node:12585645437","kind":"peak","name":"Puy de Liège","lat":44.9323421,"lon":1.4171475,"elevationM":292},{"id":"node:12585645438","kind":"peak","name":"le Pas du Raysse","lat":44.885876,"lon":1.442286,"elevationM":91},{"id":"node:12585645439","kind":"peak","name":"Pech Pialat","lat":44.9631502,"lon":1.4439429,"elevationM":271},{"id":"node:12585645440","kind":"peak","name":"Pech Redon","lat":44.9357382,"lon":1.5062736,"elevationM":311},{"id":"node:12585646084","kind":"peak","name":"Pech Redon","lat":44.9702667,"lon":1.5674627,"elevationM":281},{"id":"node:12585646085","kind":"peak","name":"Puy Gastal","lat":44.9642966,"lon":1.6429926,"elevationM":336},{"id":"node:12585646086","kind":"peak","name":"Puy Tilliry","lat":44.9266823,"lon":1.6121519,"elevationM":303},{"id":"node:12585646087","kind":"peak","name":"Pecg Lamat","lat":44.9236977,"lon":1.6035261,"elevationM":267},{"id":"node:12585646088","kind":"peak","name":"la Fajole","lat":44.9040047,"lon":1.5780186,"elevationM":253},{"id":"node:12585646089","kind":"peak","name":"les Peyruges","lat":44.9017995,"lon":1.5629854,"elevationM":285},{"id":"node:12585646090","kind":"peak","name":"Pech Maury","lat":44.8938236,"lon":1.5530706,"elevationM":269},{"id":"node:12585646091","kind":"peak","name":"Pech Grand","lat":44.8854543,"lon":1.559285,"elevationM":214},{"id":"node:12585809059","kind":"peak","name":"le Pech","lat":44.8984922,"lon":1.6657135,"elevationM":null},{"id":"node:12585809060","kind":"peak","name":"Pech de Béxène","lat":44.8930707,"lon":1.7088765,"elevationM":321},{"id":"node:12585809061","kind":"peak","name":"Pech de Betou","lat":44.8839285,"lon":1.7426123,"elevationM":null},{"id":"node:12585809062","kind":"peak","name":"Pouch de Sauvy","lat":44.9489747,"lon":1.7470645,"elevationM":201},{"id":"node:12585809063","kind":"peak","name":"Puy de Liourdres","lat":44.9293117,"lon":1.7865568,"elevationM":null},{"id":"node:12585809064","kind":"peak","name":"Puy la Serre","lat":44.9444128,"lon":1.8201396,"elevationM":225},{"id":"node:12592907200","kind":"peak","name":"Pech Laval","lat":44.6367713,"lon":1.9090692,"elevationM":333},{"id":"node:12592916741","kind":"peak","name":"Pech Favard","lat":44.5628584,"lon":1.9292567,"elevationM":391},{"id":"node:12593784828","kind":"peak","name":"Puy de Castel","lat":44.9575853,"lon":1.962223,"elevationM":415},{"id":"node:12837567638","kind":"peak","name":"Point culminant du 47","lat":44.5957826,"lon":1.0729997,"elevationM":285},{"id":"node:13012198843","kind":"peak","name":"Pech del Rieu","lat":44.9607601,"lon":1.9932565,"elevationM":525},{"id":"node:13014152731","kind":"peak","name":"Pech des Rouquétes","lat":44.9563846,"lon":1.994144,"elevationM":562},{"id":"node:13014153019","kind":"peak","name":"Pech de las Croses","lat":44.952163,"lon":1.9993476,"elevationM":563},{"id":"node:13136155686","kind":"peak","name":"Pech Delrieu","lat":44.9238259,"lon":1.9666549,"elevationM":521},{"id":"node:13149512712","kind":"peak","name":"Pech de Tourau","lat":44.918141,"lon":1.9625973,"elevationM":521},{"id":"node:13171694422","kind":"peak","name":"Pech de Fourches","lat":44.9217909,"lon":1.9454021,"elevationM":492},{"id":"node:13175489143","kind":"peak","name":"Pech de Planevergne","lat":44.9323962,"lon":1.9426279,"elevationM":437},{"id":"node:13176497752","kind":"peak","name":"Pech de Montillau","lat":44.9333501,"lon":1.945148,"elevationM":436},{"id":"node:13184283426","kind":"peak","name":"Pech du Moulin","lat":44.9031694,"lon":1.9743701,"elevationM":507},{"id":"node:13190272807","kind":"peak","name":"Pech Desquié","lat":44.9063648,"lon":1.9697843,"elevationM":500},{"id":"node:13190784012","kind":"peak","name":"Puech de la Bessière","lat":44.9114247,"lon":1.9878818,"elevationM":525},{"id":"node:13203001293","kind":"peak","name":"Puech Carayrou","lat":44.9182754,"lon":1.9841327,"elevationM":540},{"id":"node:13235384324","kind":"peak","name":"Pech Grand","lat":44.9384613,"lon":1.9634061,"elevationM":521},{"id":"node:13306402354","kind":"peak","name":"Puech de la Coné","lat":44.8792628,"lon":1.992717,"elevationM":550},{"id":"node:13386836320","kind":"peak","name":"Puech de la Marquise","lat":44.8716867,"lon":1.999741,"elevationM":549},{"id":"node:13447783532","kind":"peak","name":"Puech Lafon","lat":44.8608785,"lon":1.9923174,"elevationM":543},{"id":"node:13719167322","kind":"peak","name":"Puech de Besse","lat":44.8485322,"lon":1.9925549,"elevationM":540}]}